{
    "title": "国模龙园园宾馆大尺度人体私拍套图",
    "hash": "61eda7fb1e63e",
    "root": "https://img.xchina.fun/photos/61eda7fb1e63e/",
    "data": [
        {
            "title": "1",
            "thumbnail": "0001_300x0.jpg",
            "enlarged": "0001.jpg",
            "tWidth": 300,
            "tHeight": 200,
            "eWidth": 2400,
            "eHeight": 1600
        },
        {
            "title": "2",
            "thumbnail": "0002_300x0.jpg",
            "enlarged": "0002.jpg",
            "tWidth": 300,
            "tHeight": 450,
            "eWidth": 1600,
            "eHeight": 2400
        }
    ]
}